{"cameraMode":{"drawMode":0,"name":"Shaded","section":"Shading Mode"},"sceneLighting":true,"audioPlay":false,"sceneViewState":{"m_AlwaysRefresh":false,"showFog":true,"showSkybox":true,"showFlares":true,"showImageEffects":true,"showParticleSystems":true,"showVisualEffectGraphs":true,"m_FxEnabled":true},"in2DMode":false,"pivot":{"x":130.28643798828126,"y":9.954986572265625,"z":92.50261688232422},"rotation":{"x":0.5283293128013611,"y":-0.4701347053050995,"z":0.5262031555175781,"w":0.47224846482276919},"size":141.7083740234375,"orthographic":false}